pyanomaly/__init__.py
pyanomaly/analytics.py
pyanomaly/characteristics.py
pyanomaly/config.py
pyanomaly/datatools.py
pyanomaly/datatypes.py
pyanomaly/factors.py
pyanomaly/ff.py
pyanomaly/fileio.py
pyanomaly/globals.py
pyanomaly/log.py
pyanomaly/numba_support.py
pyanomaly/panel.py
pyanomaly/portfolio.py
pyanomaly/tcost.py
pyanomaly/util.py
pyanomaly/wrdsdata.py
pyassetpricing-1.1.dist-info/LICENSE.txt
pyassetpricing-1.1.dist-info/METADATA
pyassetpricing-1.1.dist-info/WHEEL
pyassetpricing-1.1.dist-info/top_level.txt
pyassetpricing-1.1.dist-info/RECORD
