Metadata-Version: 2.1
Name: pyassetpricing
Version: 1.1
Summary: Python library for asset pricing research
Home-page: https://github.com/chulwoohan/pyanomaly
Author: Chulwoo Han and Jongho Kang
Author-email: chulwoo.han@skku.edu
Project-URL: Documentation, https://pyanomaly.readthedocs.io/en/latest/index.html
Classifier: Programming Language :: Python :: 3.10
Classifier: License :: OSI Approved :: MIT License
Classifier: Operating System :: OS Independent
Requires-Python: >=3.9
License-File: LICENSE.txt
Requires-Dist: wrds
Requires-Dist: openpyxl
Requires-Dist: pandas
Requires-Dist: statsmodels
Requires-Dist: numba
Requires-Dist: matplotlib
Requires-Dist: scikit-learn
Requires-Dist: pyarrow
